mopidy_advanced_scrobbler/__init__.py
mopidy_advanced_scrobbler/_config.py
mopidy_advanced_scrobbler/_service.py
mopidy_advanced_scrobbler/commands.py
mopidy_advanced_scrobbler/db.py
mopidy_advanced_scrobbler/ext.conf
mopidy_advanced_scrobbler/frontend.py
mopidy_advanced_scrobbler/models.py
mopidy_advanced_scrobbler/network.py
mopidy_advanced_scrobbler/schema.py
mopidy_advanced_scrobbler/serial.py
mopidy_advanced_scrobbler/web.py
mopidy_advanced_scrobbler/_commands/__init__.py
mopidy_advanced_scrobbler/_commands/output.py
mopidy_advanced_scrobbler/_commands/db/__init__.py
mopidy_advanced_scrobbler/_commands/db/sync_corrections.py
mopidy_advanced_scrobbler/sql/schema.sql
mopidy_advanced_scrobbler/static/favicon.png
mopidy_advanced_scrobbler/static/index.html
mopidy_advanced_scrobbler/static/css/app.d2cf2a18.css
mopidy_advanced_scrobbler/static/css/chunk-vendors.52f87e65.css
mopidy_advanced_scrobbler/static/fonts/LatoLatin-Regular.3cd36578.woff2
mopidy_advanced_scrobbler/static/fonts/LatoLatin-Semibold.008763cc.woff2
mopidy_advanced_scrobbler/static/js/app.7ca49595.js
mopidy_advanced_scrobbler/static/js/app.7ca49595.js.map
mopidy_advanced_scrobbler/static/js/chunk-vendors.f72fa369.js
mopidy_advanced_scrobbler/static/js/chunk-vendors.f72fa369.js.map
Mopidy_Advanced_Scrobbler-2.1.0.dist-info/LICENSE
Mopidy_Advanced_Scrobbler-2.1.0.dist-info/METADATA
Mopidy_Advanced_Scrobbler-2.1.0.dist-info/WHEEL
Mopidy_Advanced_Scrobbler-2.1.0.dist-info/entry_points.txt
Mopidy_Advanced_Scrobbler-2.1.0.dist-info/top_level.txt
Mopidy_Advanced_Scrobbler-2.1.0.dist-info/RECORD
